[
  {
    "name": "BangPypers",
    "url": "https://bangalore.pythonindia.org/",
    "image": "partners/bangpypers.png"
  },
  {
    "name": "HydPy",
    "url": "https://www.hydpy.org/",
    "image": "partners/hydpy.png"
  },
  {
    "name": "PythonPune",
    "url": "https://pythonpune.in/",
    "image": "partners/PythonPune_banner.svg"
  },
  {
    "name": "PyLadies India",
    "url": "https://x.com/pyladiesi",
    "image": "partners/pyladies.jpg"
  },
  {
    "name": "ChennaiPy",
    "url": "https://chennaipy.org",
    "image": "partners/chennaipy.png"
  },
  {
    "name": "PyDelhi",
    "url": "https://pydelhi.org/",
    "image": "partners/pydelhi.jpeg"
  },
  {
    "name": "MUMPY",
    "url": "https://mumbai.pythonindia.org/",
    "image": "partners/logo_mumpy.png"
  },
  {
    "name": "Djangogirls Bangalore",
    "url": "https://x.com/DjangoGirlsBLR",
    "image": "partners/djangogirlsblr.png"
  }
]